iotbot/__init__.py
iotbot/__main__.py
iotbot/action.py
iotbot/cli.py
iotbot/client.py
iotbot/config.py
iotbot/decorators.py
iotbot/exceptions.py
iotbot/logger.py
iotbot/macro.py
iotbot/model.py
iotbot/plugin.py
iotbot/refine.py
iotbot/sugar.py
iotbot/template.py
iotbot/typing.py
iotbot/utils.py
iotbot/version.py
iotbot/webhook.py
python_iotbot-2.7.4.dist-info/LICENSE
python_iotbot-2.7.4.dist-info/METADATA
python_iotbot-2.7.4.dist-info/WHEEL
python_iotbot-2.7.4.dist-info/entry_points.txt
python_iotbot-2.7.4.dist-info/top_level.txt
python_iotbot-2.7.4.dist-info/RECORD
