Metadata-Version: 2.1
Name: python-iotbot
Version: 2.7.4
Summary: IOTBOT SDK with python!
Home-page: https://github.com/XiyaoWong/python-iotbot
Author: wongxy
Author-email: xiyao.wong@foxmail.com
License: MIT
Keywords: iotbot,iotbot sdk,iotqq,OPQ,OPQBot
Platform: UNKNOWN
Classifier: Programming Language :: Python :: 3.6
Classifier: Programming Language :: Python :: 3.7
Classifier: Programming Language :: Python :: 3.8
Classifier: Programming Language :: Python :: Implementation :: PyPy
Classifier: Intended Audience :: Developers
Classifier: Intended Audience :: System Administrators
Classifier: License :: OSI Approved :: MIT License
Classifier: Operating System :: OS Independent
Requires-Python: >=3.6
Requires-Dist: python-socketio (>=4.5.1)
Requires-Dist: websocket-client (>=0.57.0)
Requires-Dist: requests (>=2.23.0)
Requires-Dist: prettytable (>=0.7.2)
Requires-Dist: loguru (>=0.5.1)
